UniversalIMG-1.2.2.data/data/pyimgedit/freimgedcs.exe
UniversalIMG-1.2.2.data/data/pyimgedit/icon.png
pyimgedit/__init__.py
pyimgedit/__main__.py
pyimgedit/gui/__init__.py
pyimgedit/gui/archive_data_view.py
pyimgedit/gui/archive_info_view.py
pyimgedit/gui/archive_log_view.py
pyimgedit/gui/custom_widgets.py
UniversalIMG-1.2.2.dist-info/LICENSE
UniversalIMG-1.2.2.dist-info/METADATA
UniversalIMG-1.2.2.dist-info/WHEEL
UniversalIMG-1.2.2.dist-info/top_level.txt
UniversalIMG-1.2.2.dist-info/RECORD
