Metadata-Version: 2.1
Name: UniversalIMG
Version: 1.2.2
Summary: Open & edit .img files for gta III / VC / SA (+GUI)
Author: Nikita (NIKDISSV)
Author-email: nikdissv@proton.me
License: MIT
Classifier: Development Status :: 4 - Beta
Classifier: Topic :: Desktop Environment
Classifier: Operating System :: Microsoft :: Windows
Classifier: Programming Language :: Python :: 3.10
Requires-Python: >=3.10
License-File: LICENSE
Requires-Dist: html-table-parser-python3
Provides-Extra: all
Requires-Dist: html-table-parser-python3 ; extra == 'all'
Requires-Dist: darkdetect ; extra == 'all'
Requires-Dist: kivymd ; extra == 'all'
Requires-Dist: Kivy ; extra == 'all'
Provides-Extra: gui
Requires-Dist: darkdetect ; extra == 'gui'
Requires-Dist: kivymd ; extra == 'gui'
Requires-Dist: Kivy ; extra == 'gui'
